[
  {
    "FieldName": "CardCode",
    "Label": "Customer",
    "FieldType": "textfield",
    "ColumnWidth": 2,
    "Visible": "Y",
    "Readonly": "N",
    "Required": "N",
    "data": null,
    "TabID": null,
    "Location": 0,
    "Position": "L",
    "ClickEvent": "openBp"
  },
  {
    "FieldName": "CardName",
    "FieldType": "textfield",
    "Label": "Customer Name",
    "ColumnWidth": 2,
    "Visible": "Y",
    "Readonly": "Y",
    "Required": "N",
    "data": null,
    "TabID": null,
    "Position": "L",
    "Location": 0
  },
  {
    "FieldName": "ReqType",
    "Label": "Req. Type",
    "FieldType": "select",
    "ColumnWidth": 2,
    "Visible": "N",
    "Readonly": "N",
    "Required": "N",
    "ItemText": "Name",
    "ItemValue": "value",
    "data": "reqTypes",
    "TabID": null,
    "Position": "L",
    "Location": 0
  },
  {
    "FieldName": "Branch",
    "Label": "Branch",
    "FieldType": "select",
    "ColumnWidth": 2,
    "Visible": "N",
    "Readonly": "N",
    "Required": "N",
    "ItemText": "Name",
    "ItemValue": "value",
    "data": null,
    "TabID": null,
    "Position": "L",
    "Location": 1
  },

  {
    "FieldName": "Requester",
    "Label": "Requester",
    "FieldType": "select",
    "ColumnWidth": 2,
    "Visible": "N",
    "Readonly": "N",
    "Required": "N",
    "ItemText": "Name",
    "ItemValue": "value",
    "data": null,
    "TabID": null,
    "Location": 0,
    "Position": "L"
  },

  {
    "FieldName": "Department",
    "Label": "Department",
    "FieldType": "select",
    "ColumnWidth": 2,
    "Visible": "N",
    "Readonly": "N",
    "Required": "N",
    "ItemText": "Name",
    "ItemValue": "value",
    "data": "requesters",
    "TabID": null,
    "Position": "L",
    "Location": 0
  },

  {
    "FieldName": "Branch",
    "Label": "Branch",
    "FieldType": "select",
    "ColumnWidth": 2,
    "Visible": "N",
    "Readonly": "N",
    "Required": "N",
    "ItemText": "Name",
    "ItemValue": "value",
    "data": "requesters",
    "TabID": null,
    "Position": "R",
    "Location": 0
  },

  {
    "FieldName": "CntctCode",
    "Label": "Contact Person",
    "FieldType": "textfield",
    "ColumnWidth": 2,
    "Visible": "Y",
    "Readonly": "N",
    "Required": "N",
    "data": null,
    "TabID": null,
    "Position": "L",
    "Location": 0
  },
  {
    "FieldName": "NumAtCard",
    "Label": "Customer RefNo",
    "FieldType": "textfield",
    "ColumnWidth": 2,
    "Visible": "Y",
    "Readonly": "N",
    "Required": "N",
    "data": null,
    "TabID": null,
    "Position": "L",
    "Location": 0
  },
  {
    "FieldName": "CurSource",
    "Label": "Currency Source",
    "FieldType": "select",
    "ColumnWidth": 2,
    "Visible": "N",
    "Readonly": "N",
    "Required": "N",
    "data": "curSources",
    "TabID": null,
    "Position": "L",
    "Location": 0
  },
  {
    "FieldName": "Series",
    "Label": "Series",
    "FieldType": "select",
    "ColumnWidth": 2,
    "Visible": "Y",
    "Readonly": "N",
    "Required": "N",
    "data": "seriesData",
    "TabID": null,
    "Position": "R",
    "Location": 0
  },

  {
    "FieldName": "DocNum",
    "Label": "Doc No.",
    "FieldType": "textfield",
    "ColumnWidth": 2,
    "Visible": "Y",
    "Readonly": "N",
    "Required": "N",
    "data": null,
    "TabID": null,
    "Position": "R",
    "Location": 0
  },
  {
    "FieldName": "DocStatus",
    "Label": "Status",
    "FieldType": "textfield",
    "ColumnWidth": 2,
    "Visible": "Y",
    "Readonly": "Y",
    "Required": "Y",
    "data": "status",
    "TabID": null,
    "Position": "R",
    "Location": 0
  },

  {
    "FieldName": "DocDate",
    "Label": "Posting Date",
    "FieldType": "date",
    "ColumnWidth": 2,
    "Visible": "Y",
    "Readonly": "N",
    "Required": "N",
    "data": null,
    "TabID": null,
    "Position": "R",
    "Location": 0
  },
  {
    "FieldName": "TaxDate",
    "Label": "Document Date",
    "FieldType": "date",
    "ColumnWidth": 2,
    "Visible": "Y",
    "Readonly": "N",
    "Required": "N",
    "data": null,
    "TabID": null,
    "Position": "R",
    "Location": 0
  },
  {
    "FieldName": "DocDueDate",
    "Label": "Delivery Date",
    "FieldType": "date",
    "ColumnWidth": 2,
    "Visible": "Y",
    "Readonly": "N",
    "Required": "N",
    "data": null,
    "TabID": null,
    "Position": "R",
    "Location": 0
  },
  {
    "FieldName": "ReqDate",
    "Label": "Required Date",
    "FieldType": "date",
    "ColumnWidth": 2,
    "Visible": "N",
    "Readonly": "N",
    "Required": "N",
    "data": null,
    "TabID": null,
    "Position": "R",
    "Location": 0
  },

  {
    "FieldName": "BPLId",
    "FieldType": "select",
    "Label": "Branch",
    "ColumnWidth": 2,
    "Visible": "Y",
    "Readonly": "N",
    "Required": "Y",
    "data": "branchesData",
    "TabID": null,
    "Position": "R",
    "Location": 0
  },

  {
    "FieldName": "PriceList",
    "Label": "Price List",
    "FieldType": "select",
    "ColumnWidth": 2,
    "Visible": "N",
    "Readonly": "N",
    "Required": "N",
    "ItemText": "ListName",
    "ItemValue": "id",
    "data": "priceLists",
    "TabID": null,
    "Position": "L",
    "Location": 0
  },
  {
    "FieldName": "FromWhsCod",
    "Label": "From Warehouse",
    "FieldType": "select",
    "ColumnWidth": 2,
    "Visible": "N",
    "Readonly": "N",
    "Required": "N",
    "ItemText": "WhsName",
    "ItemValue": "id",
    "data": "warehouses",
    "TabID": null,
    "Position": "R",
    "Location": 0
  },
  {
    "FieldName": "LicTradNum",
    "FieldType": "textfield",
    "Label": "KRA Pin",
    "ColumnWidth": 2,
    "Visible": "Y",
    "Readonly": "N",
    "Required": "N",
    "data": null,
    "TabID": null,
    "Position": "L",
    "Location": 0
  },

  {
    "FieldName": "NumAtCard2",
    "Label": "Delear Name",
    "FieldType": "select",
    "ColumnWidth": 2,
    "Visible": "Y",
    "Readonly": "N",
    "Required": "N",
    "ItemText": "Name",
    "ItemValue": "Name",
    "data": "delears",
    "TabID": null,
    "Position": "R",
    "Location": 0
  },
  {
    "FieldName": "ToWhsCode",
    "Label": "To Warehouse",
    "FieldType": "select",
    "ColumnWidth": 2,
    "Visible": "N",
    "Readonly": "N",
    "Required": "N",
    "ItemText": "WhsName",
    "ItemValue": "id",
    "data": "warehouses",
    "TabID": null,
    "Position": "R",
    "Location": 0
  },

  {
    "FieldName": "DocType",
    "Label": "Doc Type",
    "FieldType": "select",
    "ColumnWidth": 2,
    "Visible": "N",
    "Readonly": "N",
    "Required": "N",
    "ItemText": "Name",
    "ItemValue": "id",
    "data": "doctypes",
    "TabID": null,
    "Position": "R",
    "Location": 0
  },

  {
    "FieldName": "SlpCode",
    "Label": "Sales Employee",
    "FieldType": "select",
    "ColumnWidth": 2,
    "Visible": "Y",
    "Readonly": "Y",
    "Required": "N",
    "data": null,
    "TabID": null,
    "Location": 1
  },
  {
    "FieldName": "OwnerCode",
    "Label": "Document Owner",
    "FieldType": "textfield",
    "ColumnWidth": 2,
    "Visible": "Y",
    "Readonly": "Y",
    "Required": "N",
    "data": null,
    "TabID": null,
    "Location": 1
  },
  {
    "FieldName": "Comments",
    "Label": "Remarks",
    "FieldType": "textarea",
    "ColumnWidth": 2,
    "Visible": "Y",
    "Readonly": "Y",
    "Required": "N",
    "data": null,
    "TabID": null,
    "Location": 1
  },
  {
    "FieldName": "TotalBeforeDiscount",
    "Label": "Total Before Discount",
    "FieldType": "textfield",
    "ColumnWidth": 2,
    "Visible": "N",
    "Readonly": "Y",
    "Required": "N",
    "data": null,
    "TabID": null,
    "Location": 1
  },

  {
    "FieldName": "Discount",
    "Label": "Discount",
    "FieldType": "textfield",
    "ColumnWidth": 2,
    "Visible": "N",
    "Readonly": "Y",
    "Required": "N",
    "data": null,
    "TabID": null,
    "Location": 1
  },
  {
    "FieldName": "DiscountAmount",
    "Label": "Discount Amount",
    "FieldType": "textfield",
    "ColumnWidth": 2,
    "Visible": "N",
    "Readonly": "Y",
    "Required": "N",
    "data": null,
    "TabID": null,
    "Location": 1
  },
  {
    "FieldName": "TotalDownPaymnet",
    "Label": "Total Down Paymnet",
    "FieldType": "textfield",
    "ColumnWidth": 2,
    "Visible": "N",
    "Readonly": "Y",
    "Required": "N",
    "data": null,
    "TabID": null,
    "Location": 1
  },
  {
    "FieldName": "DiscPrcnt",
    "Label": "Discount %",
    "FieldType": "textfield",
    "ColumnWidth": 2,
    "Visible": "Y",
    "Readonly": "N",
    "Required": "N",
    "data": null,
    "TabID": null,
    "Location": 1
  },
  {
    "FieldName": "DiscSum",
    "Label": "Discount Amount",
    "FieldType": "textfield",
    "ColumnWidth": 2,
    "Visible": "Y",
    "Readonly": "Y",
    "Required": "N",
    "data": null,
    "TabID": null,
    "Location": 1
  },
  {
    "FieldName": "VatSum",
    "Label": "Vat",
    "FieldType": "textfield",
    "ColumnWidth": 2,
    "Visible": "N",
    "Readonly": "Y",
    "Required": "N",
    "data": null,
    "TabID": null,
    "Location": 1
  },
  {
    "FieldName": "DocTotal",
    "Label": "Total",
    "FieldType": "textfield",
    "ColumnWidth": 2,
    "Visible": "Y",
    "Readonly": "Y",
    "Required": "N",
    "data": null,
    "TabID": null,
    "Location": 1
  },
  {
    "FieldName": "ExtRef",
    "Label": "External Reference",
    "FieldType": "textfield",
    "ColumnWidth": 2,
    "Visible": "Y",
    "Readonly": "Y",
    "Required": "N",
    "data": null,
    "TabID": null,
    "Location": 1
  },

  {
    "FieldName": "UseShpdGd",
    "Label": "Use Shipped Goods Account",
    "FieldType": "checkbox",
    "ColumnWidth": 2,
    "Visible": "Y",
    "Readonly": "Y",
    "Required": "N",
    "data": null,
    "TabID": 2,
    "Location": 1
  }
]
